hdijupyterutils/__init__.py
hdijupyterutils/configuration.py
hdijupyterutils/constants.py
hdijupyterutils/events.py
hdijupyterutils/eventshandler.py
hdijupyterutils/filehandler.py
hdijupyterutils/filesystemreaderwriter.py
hdijupyterutils/guid.py
hdijupyterutils/ipythondisplay.py
hdijupyterutils/ipywidgetfactory.py
hdijupyterutils/log.py
hdijupyterutils/utils.py
hdijupyterutils-0.23.0.dist-info/LICENSE.md
hdijupyterutils-0.23.0.dist-info/METADATA
hdijupyterutils-0.23.0.dist-info/WHEEL
hdijupyterutils-0.23.0.dist-info/top_level.txt
hdijupyterutils-0.23.0.dist-info/RECORD
